{
    "name": "nikon-ti-ctrl",
    "version": "0.2.1",
    "builtin-baseline": "b86c0c35b88e2bf3557ff49dc831689c2f085090",
    "dependencies": [
        "fmt",
        "nlohmann-json",
        {
            "name": "grpc",
            "features": [
                "codegen"
            ]
        },
        {
            "name": "tiff",
            "features": [
                "jpeg",
                "zip",
                "zstd"
            ],
            "default-features": false
        },
        {
            "name": "opencv4",
            "default-features": false
        }
    ],
    "overrides": [
        {
          "name": "fmt", "version": "7.1.3"
        }
    ]
}
